markyp_rss/__init__.py
markyp_rss/elements.py
markyp_rss-0.1910.0.dist-info/LICENSE
markyp_rss-0.1910.0.dist-info/METADATA
markyp_rss-0.1910.0.dist-info/WHEEL
markyp_rss-0.1910.0.dist-info/top_level.txt
markyp_rss-0.1910.0.dist-info/RECORD
